<?xml version="1.0" encoding="UTF-8"?>
<!-- <!DOCTYPE suite SYSTEM "http://testng.org/testng-1.0.dtd" > -->
<!DOCTYPE suite SYSTEM "https://testng.org/testng-1.0.dtd" >
<suite name="TestSuite" parallel="tests" thread-count="2">
	
	<listeners>
<!-- 		<listener class-name="com.jostens.qa.analyzer.MyTransformer"></listener> -->
		<listener class-name="com.mymatrix.qa.util.Listeners"></listener>
	</listeners>
	
	<test name="Regression Chrome">
		
		<parameter name="dataTable" value="\src\main\java\com\mymatrix\qa\testdata\Windows Patch.xlsx"></parameter>
		
		<classes>
			<class name="com.mymatrix.qa.testcases.LoginPageTest"></class>
		</classes>
	</test>
	
</suite>